{
  "data": [
    {
      "transactionId": [
        {
          "key": "pk_CampoUm",
          "value": "ABC"
        },
        {
          "key": "pk_CampoDois",
          "value": "123"
        }
      ],
      "type": "ENTRADA",
      "transactionType": "AMORTIZACAO",
      "transactionConversionDate": "2023-01-07",
      "transactionQuotaPrice": {
        "amount": "1000.04",
        "currency": "BRL"
      },
      "transactionQuotaQuantity": "42.25",
      "transactionValue": {
        "amount": "1000.04",
        "currency": "BRL"
      },
      "transactionGrossValue": {
        "amount": "1000.04",
        "currency": "BRL"
      },
      "transactionTypeAdditionalInfo": "lApk",
      "transactionNetValue": {
        "amount": "1000.04",
        "currency": "BRL"
      },
      "incomeTax": {
        "amount": "1000.04",
        "currency": "BRL"
      },
      "transactionExitFee": {
        "amount": "1000.04",
        "currency": "BRL"
      },
      "financialTransactionTax": {
        "amount": "1000.04",
        "currency": "BRL"
      }
    },
    {
      "transactionId": [
        {
          "key": "pk_CampoUm",
          "value": "ABC"
        },
        {
          "key": "pk_CampoDois",
          "value": "123"
        }
      ],
      "type": "ENTRADA",
      "transactionType": "AMORTIZACAO",
      "transactionConversionDate": "2023-01-07",
      "transactionQuotaPrice": {
        "amount": "1000.04",
        "currency": "BRL"
      },
      "transactionQuotaQuantity": "42.25",
      "transactionValue": {
        "amount": "1000.04",
        "currency": "BRL"
      },
      "transactionGrossValue": {
        "amount": "1000.04",
        "currency": "BRL"
      },
      "transactionTypeAdditionalInfo": "`'[",
      "transactionExitFee": {
        "amount": "1000.04",
        "currency": "BRL"
      },
      "incomeTax": {
        "amount": "1000.04",
        "currency": "BRL"
      },
      "transactionNetValue": {
        "amount": "1000.04",
        "currency": "BRL"
      },
      "financialTransactionTax": {
        "amount": "1000.04",
        "currency": "BRL"
      }
    },
    {
      "transactionId": [
        {
          "key": "pk_CampoUm",
          "value": "ABC"
        },
        {
          "key": "pk_CampoDois",
          "value": "123"
        }
      ],
      "type": "ENTRADA",
      "transactionType": "AMORTIZACAO",
      "transactionConversionDate": "2023-01-07",
      "transactionQuotaPrice": {
        "amount": "1000.04",
        "currency": "BRL"
      },
      "transactionQuotaQuantity": "42.25",
      "transactionValue": {
        "amount": "1000.04",
        "currency": "BRL"
      },
      "transactionGrossValue": {
        "amount": "1000.04",
        "currency": "BRL"
      },
      "incomeTax": {
        "amount": "1000.04",
        "currency": "BRL"
      },
      "transactionTypeAdditionalInfo": "mso&uzOI",
      "transactionNetValue": {
        "amount": "1000.04",
        "currency": "BRL"
      },
      "transactionExitFee": {
        "amount": "1000.04",
        "currency": "BRL"
      },
      "financialTransactionTax": {
        "amount": "1000.04",
        "currency": "BRL"
      }
    }
  ],
  "meta": {
    "hasMoreRecords": true,
    "requestDateTime": true
  }
}