{
  "data": {
    "typeContractRemaining": "ANO",
    "typeNumberOfInstalments": "MES",
    "paidInstalments": 73,
    "pastDueInstalments": 73,
    "totalNumberOfInstalments": 130632,
    "contractRemainingNumber": 14600,
    "balloonPayments": [
      {
        "dueDate": "2020-01-10",
        "amount": {
          "amount": "1000.0400",
          "currency": "BRL"
        }
      },
      {
        "dueDate": "2020-01-10",
        "amount": {
          "amount": "1000.0400",
          "currency": "BRL"
        }
      },
      {
        "dueDate": "2020-01-10",
        "amount": {
          "amount": "1000.0400",
          "currency": "BRL"
        }
      },
      {
        "dueDate": "2020-01-10",
        "amount": {
          "amount": "1000.0400",
          "currency": "BRL"
        }
      },
      {
        "dueDate": "2020-01-10",
        "amount": {
          "amount": "1000.0400",
          "currency": "BRL"
        }
      }
    ],
    "dueInstalments": 57
  },
  "meta": {
    "totalRecords": 1,
    "totalPages": 1
  }
}